llama_index/packs/arize_phoenix_query_engine/__init__.py
llama_index/packs/arize_phoenix_query_engine/base.py
llama_index_packs_arize_phoenix_query_engine-0.4.1.dist-info/METADATA
llama_index_packs_arize_phoenix_query_engine-0.4.1.dist-info/WHEEL
llama_index_packs_arize_phoenix_query_engine-0.4.1.dist-info/licenses/LICENSE
llama_index_packs_arize_phoenix_query_engine-0.4.1.dist-info/RECORD
