Metadata-Version: 2.4
Name: llama-index-packs-arize-phoenix-query-engine
Version: 0.4.1
Summary: llama-index packs arize_phoenix_query_engine integration
Author-email: Your Name <you@example.com>
Maintainer: axiomofjoy
License-Expression: GPL-3.0-or-later
License-File: LICENSE
Keywords: arize,engine,index,phoenix,query
Requires-Python: <3.12,>=3.9
Requires-Dist: llama-index-callbacks-arize-phoenix<0.7,>=0.6.0
Requires-Dist: llama-index-core<0.15,>=0.13.0
Requires-Dist: llama-index-readers-web<0.6,>=0.5.0
